marbles.core-0.12.3-py3.9-nspkg.pth
marbles/__main__.py
marbles/setuptools.py
marbles/core/VERSION
marbles/core/__init__.py
marbles/core/_stack.py
marbles/core/_version.py
marbles/core/log.py
marbles/core/main.py
marbles/core/marbles.py
marbles.core-0.12.3.dist-info/LICENSE
marbles.core-0.12.3.dist-info/METADATA
marbles.core-0.12.3.dist-info/WHEEL
marbles.core-0.12.3.dist-info/entry_points.txt
marbles.core-0.12.3.dist-info/namespace_packages.txt
marbles.core-0.12.3.dist-info/top_level.txt
marbles.core-0.12.3.dist-info/RECORD
