Metadata-Version: 2.1
Name: marbles.core
Version: 0.12.3
Summary: A unittest extension that provides additional information on test failure
Home-page: https://github.com/twosigma/marbles
Download-URL: https://github.com/twosigma/marbles/archive/0.12.3.tar.gz
Author: Jane Adams, Leif Walsh
Author-email: jane@twosigma.com, leif@twosigma.com
License: MIT
Project-URL: Documentation, https://marbles.readthedocs.io
Project-URL: Source, https://github.com/twosigma/marbles
Project-URL: Tracker, https://github.com/twosigma/marbles/issues
Classifier: Development Status :: 5 - Production/Stable
Classifier: Environment :: Console
Classifier: Framework :: Setuptools Plugin
Classifier: Intended Audience :: Developers
Classifier: Intended Audience :: Financial and Insurance Industry
Classifier: Intended Audience :: Healthcare Industry
Classifier: Intended Audience :: Information Technology
Classifier: Intended Audience :: Manufacturing
Classifier: Intended Audience :: Science/Research
Classifier: Intended Audience :: System Administrators
Classifier: License :: OSI Approved :: MIT License
Classifier: Natural Language :: English
Classifier: Operating System :: OS Independent
Classifier: Programming Language :: Python :: 3.9
Classifier: Programming Language :: Python :: 3.10
Classifier: Programming Language :: Python :: 3.11
Classifier: Programming Language :: Python :: 3.12
Classifier: Topic :: Documentation
Classifier: Topic :: Scientific/Engineering
Classifier: Topic :: Software Development :: Libraries :: Python Modules
Classifier: Topic :: Software Development :: Testing
License-File: LICENSE
